[
  {
    "url": "https://actc.org.ar/v3/carrera-on-line-resultados.ajax.php?intIDCarrera=1511&intIDTanda=15",
    "resultado": [
      {
        "pos": "1°",
        "nro": "197",
        "nombre": "Scialchi,",
        "apellido": "Jeremías",
        "piloto": "Scialchi, Jeremías",
        "marca": "Torino",
        "vueltas": "20",
        "tiempo": "29:36.529",
        "diferencia": "",
        "nacionalidad": "Scialchi, Jeremías"
      },
      {
        "pos": "2°",
        "nro": "3",
        "nombre": "Olmedo,",
        "apellido": "Jeremías",
        "piloto": "Olmedo, Jeremías",
        "marca": "Ford",
        "vueltas": "20",
        "tiempo": "29:40.294",
        "diferencia": "3.765",
        "nacionalidad": "Olmedo, Jeremías"
      },
      {
        "pos": "3°",
        "nro": "41",
        "nombre": "Barrio,",
        "apellido": "Jorge",
        "piloto": "Barrio, Jorge",
        "marca": "Chevrolet",
        "vueltas": "20",
        "tiempo": "29:43.033",
        "diferencia": "6.504",
        "nacionalidad": "Barrio, Jorge"
      },
      {
        "pos": "4°",
        "nro": "11",
        "nombre": "Canapino,",
        "apellido": "Matías",
        "piloto": "Canapino, Matías",
        "marca": "Chevrolet",
        "vueltas": "20",
        "tiempo": "29:49.964",
        "diferencia": "13.435",
        "nacionalidad": "Canapino, Matías"
      },
      {
        "pos": "5°",
        "nro": "14",
        "nombre": "De",
        "apellido": "Brabandere,",
        "piloto": "De Brabandere, Agustín",
        "marca": "Ford",
        "vueltas": "20",
        "tiempo": "29:51.349",
        "diferencia": "14.820",
        "nacionalidad": "De Brabandere, Agustín"
      },
      {
        "pos": "6°",
        "nro": "8",
        "nombre": "Impiombato,",
        "apellido": "Nicolás",
        "piloto": "Impiombato, Nicolás",
        "marca": "Chevrolet",
        "vueltas": "20",
        "tiempo": "29:51.710",
        "diferencia": "15.181",
        "nacionalidad": "Impiombato, Nicolás"
      },
      {
        "pos": "7°",
        "nro": "21",
        "nombre": "Pilo,",
        "apellido": "Juan",
        "piloto": "Pilo, Juan Pablo",
        "marca": "Ford",
        "vueltas": "20",
        "tiempo": "29:53.999",
        "diferencia": "17.470",
        "nacionalidad": "Pilo, Juan Pablo"
      },
      {
        "pos": "8°",
        "nro": "51",
        "nombre": "Ricciardi,",
        "apellido": "Thomas",
        "piloto": "Ricciardi, Thomas",
        "marca": "Ford",
        "vueltas": "20",
        "tiempo": "30:00.438",
        "diferencia": "23.909",
        "nacionalidad": "Ricciardi, Thomas"
      },
      {
        "pos": "9°",
        "nro": "119",
        "nombre": "Palazzo,",
        "apellido": "Hernán",
        "piloto": "Palazzo, Hernán",
        "marca": "Chevrolet",
        "vueltas": "20",
        "tiempo": "30:00.713",
        "diferencia": "24.184",
        "nacionalidad": "Palazzo, Hernán"
      },
      {
        "pos": "10°",
        "nro": "131",
        "nombre": "Rasuk,",
        "apellido": "José",
        "piloto": "Rasuk, José",
        "marca": "Dodge",
        "vueltas": "20",
        "tiempo": "30:02.020",
        "diferencia": "25.491",
        "nacionalidad": "Rasuk, José"
      },
      {
        "pos": "11°",
        "nro": "16",
        "nombre": "Valle,",
        "apellido": "Mario",
        "piloto": "Valle, Mario",
        "marca": "Chevrolet",
        "vueltas": "20",
        "tiempo": "30:02.428",
        "diferencia": "25.899",
        "nacionalidad": "Valle, Mario"
      },
      {
        "pos": "12°",
        "nro": "23",
        "nombre": "Gandulia,",
        "apellido": "Gabriel",
        "piloto": "Gandulia, Gabriel",
        "marca": "Ford",
        "vueltas": "20",
        "tiempo": "30:11.655",
        "diferencia": "35.126",
        "nacionalidad": "Gandulia, Gabriel"
      },
      {
        "pos": "13°",
        "nro": "109",
        "nombre": "Leguizamón,",
        "apellido": "Baltazar",
        "piloto": "Leguizamón, Baltazar",
        "marca": "Dodge",
        "vueltas": "20",
        "tiempo": "30:11.924",
        "diferencia": "35.395",
        "nacionalidad": "Leguizamón, Baltazar"
      },
      {
        "pos": "14°",
        "nro": "123",
        "nombre": "Gonnet,",
        "apellido": "Gerónimo",
        "piloto": "Gonnet, Gerónimo",
        "marca": "Torino",
        "vueltas": "20",
        "tiempo": "30:12.500",
        "diferencia": "35.971",
        "nacionalidad": "Gonnet, Gerónimo"
      },
      {
        "pos": "15°",
        "nro": "86",
        "nombre": "Faín,",
        "apellido": "Ignacio",
        "piloto": "Faín, Ignacio",
        "marca": "Torino",
        "vueltas": "20",
        "tiempo": "30:15.091",
        "diferencia": "38.562",
        "nacionalidad": "Faín, Ignacio"
      },
      {
        "pos": "16°",
        "nro": "32",
        "nombre": "Markel,",
        "apellido": "Damián",
        "piloto": "Markel, Damián",
        "marca": "Ford",
        "vueltas": "20",
        "tiempo": "30:16.917",
        "diferencia": "40.388",
        "nacionalidad": "Markel, Damián"
      },
      {
        "pos": "17°",
        "nro": "27",
        "nombre": "Reynoso,",
        "apellido": "Sebastián",
        "piloto": "Reynoso, Sebastián",
        "marca": "Ford",
        "vueltas": "20",
        "tiempo": "30:17.433",
        "diferencia": "40.904",
        "nacionalidad": "Reynoso, Sebastián"
      },
      {
        "pos": "18°",
        "nro": "71",
        "nombre": "Calvani,",
        "apellido": "Lucio",
        "piloto": "Calvani, Lucio",
        "marca": "Dodge",
        "vueltas": "20",
        "tiempo": "30:18.260",
        "diferencia": "41.731",
        "nacionalidad": "Calvani, Lucio"
      },
      {
        "pos": "19°",
        "nro": "178",
        "nombre": "Tomasello,",
        "apellido": "Juan",
        "piloto": "Tomasello, Juan Manuel",
        "marca": "Chevrolet",
        "vueltas": "20",
        "tiempo": "30:19.030",
        "diferencia": "42.501",
        "nacionalidad": "Tomasello, Juan Manuel"
      },
      {
        "pos": "20°",
        "nro": "140",
        "nombre": "Chansard,",
        "apellido": "Gaspar",
        "piloto": "Chansard, Gaspar",
        "marca": "Dodge",
        "vueltas": "20",
        "tiempo": "30:19.391",
        "diferencia": "42.862",
        "nacionalidad": "Chansard, Gaspar"
      },
      {
        "pos": "21°",
        "nro": "152",
        "nombre": "Martínez,",
        "apellido": "Thiago",
        "piloto": "Martínez, Thiago",
        "marca": "Ford",
        "vueltas": "20",
        "tiempo": "30:19.759",
        "diferencia": "43.230",
        "nacionalidad": "Martínez, Thiago"
      },
      {
        "pos": "22°",
        "nro": "117",
        "nombre": "Abdala,",
        "apellido": "Tomás",
        "piloto": "Abdala, Tomás",
        "marca": "Ford",
        "vueltas": "20",
        "tiempo": "30:26.744",
        "diferencia": "50.215",
        "nacionalidad": "Abdala, Tomás"
      },
      {
        "pos": "23°",
        "nro": "118",
        "nombre": "Salse,",
        "apellido": "Sebastián",
        "piloto": "Salse, Sebastián",
        "marca": "Dodge",
        "vueltas": "20",
        "tiempo": "30:36.132",
        "diferencia": "59.603",
        "nacionalidad": "Salse, Sebastián"
      },
      {
        "pos": "24°",
        "nro": "20",
        "nombre": "Teti,",
        "apellido": "Jerónimo",
        "piloto": "Teti, Jerónimo",
        "marca": "Torino",
        "vueltas": "20",
        "tiempo": "31:11.146",
        "diferencia": "1:34.617",
        "nacionalidad": "Teti, Jerónimo"
      },
      {
        "pos": "25°",
        "nro": "137",
        "nombre": "Scoltore,",
        "apellido": "Juan",
        "piloto": "Scoltore, Juan",
        "marca": "Chevrolet",
        "vueltas": "19",
        "tiempo": "30:25.170",
        "diferencia": "1 VTA",
        "nacionalidad": "Scoltore, Juan"
      },
      {
        "pos": "26°",
        "nro": "125",
        "nombre": "Beraldi,",
        "apellido": "Cristian",
        "piloto": "Beraldi, Cristian",
        "marca": "Ford",
        "vueltas": "19",
        "tiempo": "30:36.826",
        "diferencia": "1 VTA",
        "nacionalidad": "Beraldi, Cristian"
      },
      {
        "pos": "27°",
        "nro": "9",
        "nombre": "Valle,",
        "apellido": "Lucas",
        "piloto": "Valle, Lucas",
        "marca": "Dodge",
        "vueltas": "18",
        "tiempo": "27:39.953",
        "diferencia": "2 VTAS",
        "nacionalidad": "Valle, Lucas"
      },
      {
        "pos": "28°",
        "nro": "113",
        "nombre": "Lugón,",
        "apellido": "Rodrigo",
        "piloto": "Lugón, Rodrigo",
        "marca": "Ford",
        "vueltas": "16",
        "tiempo": "24:13.583",
        "diferencia": "4 VTAS",
        "nacionalidad": "Lugón, Rodrigo"
      },
      {
        "pos": "29°",
        "nro": "188",
        "nombre": "Jaime,",
        "apellido": "Alberto",
        "piloto": "Jaime, Alberto Daniel",
        "marca": "Dodge",
        "vueltas": "15",
        "tiempo": "25:05.342",
        "diferencia": "5 VTAS",
        "nacionalidad": "Jaime, Alberto Daniel"
      },
      {
        "pos": "30°",
        "nro": "159",
        "nombre": "Séfchek,",
        "apellido": "Blas",
        "piloto": "Séfchek, Blas",
        "marca": "Torino",
        "vueltas": "14",
        "tiempo": "22:06.038",
        "diferencia": "6 VTAS",
        "nacionalidad": "Séfchek, Blas"
      },
      {
        "pos": "31°",
        "nro": "25",
        "nombre": "Cotignola,",
        "apellido": "Luciano",
        "piloto": "Cotignola, Luciano",
        "marca": "Torino",
        "vueltas": "11",
        "tiempo": "17:46.987",
        "diferencia": "9 VTAS",
        "nacionalidad": "Cotignola, Luciano"
      },
      {
        "pos": "32°",
        "nro": "133",
        "nombre": "Maceira,",
        "apellido": "Juan",
        "piloto": "Maceira, Juan Ignacio",
        "marca": "Ford",
        "vueltas": "5",
        "tiempo": "11:08.913",
        "diferencia": "15 VTAS",
        "nacionalidad": "Maceira, Juan Ignacio"
      },
      {
        "pos": "33°",
        "nro": "10",
        "nombre": "Azar,",
        "apellido": "Diego",
        "piloto": "Azar, Diego",
        "marca": "Toyota",
        "vueltas": "2",
        "tiempo": "04:53.832",
        "diferencia": "18 VTAS",
        "nacionalidad": "Azar, Diego"
      },
      {
        "pos": "34°",
        "nro": "54",
        "nombre": "Ochoa,",
        "apellido": "Joaquín",
        "piloto": "Ochoa, Joaquín",
        "marca": "Dodge",
        "vueltas": "2",
        "tiempo": "05:01.082",
        "diferencia": "18 VTAS",
        "nacionalidad": "Ochoa, Joaquín"
      },
      {
        "pos": "35°",
        "nro": "193",
        "nombre": "Castro,",
        "apellido": "Marcos",
        "piloto": "Castro, Marcos",
        "marca": "Ford",
        "vueltas": "0",
        "tiempo": "",
        "diferencia": "20 VTAS",
        "nacionalidad": "Castro, Marcos"
      }
    ]
  },
  {
    "url": "https://actc.org.ar/v3/carrera-on-line-resultados.ajax.php?intIDCarrera=1512&intIDTanda=15",
    "resultado": [
      {
        "pos": "1°",
        "nro": "10",
        "nombre": "Azar,",
        "apellido": "Diego",
        "piloto": "Azar, Diego",
        "marca": "Toyota",
        "vueltas": "20",
        "tiempo": "38:19.119",
        "diferencia": "",
        "nacionalidad": "Azar, Diego"
      },
      {
        "pos": "2°",
        "nro": "119",
        "nombre": "Palazzo,",
        "apellido": "Hernán",
        "piloto": "Palazzo, Hernán",
        "marca": "Chevrolet",
        "vueltas": "20",
        "tiempo": "38:20.176",
        "diferencia": "1.057",
        "nacionalidad": "Palazzo, Hernán"
      },
      {
        "pos": "3°",
        "nro": "3",
        "nombre": "Olmedo,",
        "apellido": "Jeremías",
        "piloto": "Olmedo, Jeremías",
        "marca": "Ford",
        "vueltas": "20",
        "tiempo": "38:23.760",
        "diferencia": "4.641",
        "nacionalidad": "Olmedo, Jeremías"
      },
      {
        "pos": "4°",
        "nro": "12",
        "nombre": "Moscardini,",
        "apellido": "Nicolás",
        "piloto": "Moscardini, Nicolás",
        "marca": "Ford",
        "vueltas": "20",
        "tiempo": "38:25.270",
        "diferencia": "6.151",
        "nacionalidad": "Moscardini, Nicolás"
      },
      {
        "pos": "5°",
        "nro": "118",
        "nombre": "Salse,",
        "apellido": "Sebastián",
        "piloto": "Salse, Sebastián",
        "marca": "Dodge",
        "vueltas": "20",
        "tiempo": "38:26.466",
        "diferencia": "7.347",
        "nacionalidad": "Salse, Sebastián"
      },
      {
        "pos": "6°",
        "nro": "21",
        "nombre": "Pilo,",
        "apellido": "Juan",
        "piloto": "Pilo, Juan Pablo",
        "marca": "Ford",
        "vueltas": "20",
        "tiempo": "38:27.739",
        "diferencia": "8.620",
        "nacionalidad": "Pilo, Juan Pablo"
      },
      {
        "pos": "7°",
        "nro": "137",
        "nombre": "Scoltore,",
        "apellido": "Juan",
        "piloto": "Scoltore, Juan",
        "marca": "Chevrolet",
        "vueltas": "20",
        "tiempo": "38:29.097",
        "diferencia": "9.978",
        "nacionalidad": "Scoltore, Juan"
      },
      {
        "pos": "8°",
        "nro": "178",
        "nombre": "Tomasello,",
        "apellido": "Juan",
        "piloto": "Tomasello, Juan Manuel",
        "marca": "Chevrolet",
        "vueltas": "20",
        "tiempo": "38:30.163",
        "diferencia": "11.044",
        "nacionalidad": "Tomasello, Juan Manuel"
      },
      {
        "pos": "9°",
        "nro": "23",
        "nombre": "Gandulia,",
        "apellido": "Gabriel",
        "piloto": "Gandulia, Gabriel",
        "marca": "Ford",
        "vueltas": "20",
        "tiempo": "38:31.521",
        "diferencia": "12.402",
        "nacionalidad": "Gandulia, Gabriel"
      },
      {
        "pos": "10°",
        "nro": "197",
        "nombre": "Scialchi,",
        "apellido": "Jeremías",
        "piloto": "Scialchi, Jeremías",
        "marca": "Torino",
        "vueltas": "20",
        "tiempo": "38:32.450",
        "diferencia": "13.331",
        "nacionalidad": "Scialchi, Jeremías"
      },
      {
        "pos": "11°",
        "nro": "140",
        "nombre": "Chansard,",
        "apellido": "Gaspar",
        "piloto": "Chansard, Gaspar",
        "marca": "Dodge",
        "vueltas": "20",
        "tiempo": "38:34.105",
        "diferencia": "14.986",
        "nacionalidad": "Chansard, Gaspar"
      },
      {
        "pos": "12°",
        "nro": "32",
        "nombre": "Markel,",
        "apellido": "Damián",
        "piloto": "Markel, Damián",
        "marca": "Ford",
        "vueltas": "20",
        "tiempo": "38:40.765",
        "diferencia": "21.646",
        "nacionalidad": "Markel, Damián"
      },
      {
        "pos": "13°",
        "nro": "86",
        "nombre": "Faín,",
        "apellido": "Ignacio",
        "piloto": "Faín, Ignacio",
        "marca": "Torino",
        "vueltas": "20",
        "tiempo": "38:40.766",
        "diferencia": "21.647",
        "nacionalidad": "Faín, Ignacio"
      },
      {
        "pos": "14°",
        "nro": "16",
        "nombre": "Valle,",
        "apellido": "Mario",
        "piloto": "Valle, Mario",
        "marca": "Chevrolet",
        "vueltas": "20",
        "tiempo": "38:41.789",
        "diferencia": "22.670",
        "nacionalidad": "Valle, Mario"
      },
      {
        "pos": "15°",
        "nro": "54",
        "nombre": "Ochoa,",
        "apellido": "Joaquín",
        "piloto": "Ochoa, Joaquín",
        "marca": "Dodge",
        "vueltas": "20",
        "tiempo": "38:42.375",
        "diferencia": "23.256",
        "nacionalidad": "Ochoa, Joaquín"
      },
      {
        "pos": "16°",
        "nro": "8",
        "nombre": "Impiombato,",
        "apellido": "Nicolás",
        "piloto": "Impiombato, Nicolás",
        "marca": "Chevrolet",
        "vueltas": "20",
        "tiempo": "38:42.592",
        "diferencia": "23.473",
        "nacionalidad": "Impiombato, Nicolás"
      },
      {
        "pos": "17°",
        "nro": "193",
        "nombre": "Castro,",
        "apellido": "Marcos",
        "piloto": "Castro, Marcos",
        "marca": "Ford",
        "vueltas": "20",
        "tiempo": "38:42.722",
        "diferencia": "23.603",
        "nacionalidad": "Castro, Marcos"
      },
      {
        "pos": "18°",
        "nro": "101",
        "nombre": "Weimann,",
        "apellido": "Alejandro",
        "piloto": "Weimann, Alejandro",
        "marca": "Dodge",
        "vueltas": "20",
        "tiempo": "38:45.107",
        "diferencia": "25.988",
        "nacionalidad": "Weimann, Alejandro"
      },
      {
        "pos": "19°",
        "nro": "152",
        "nombre": "Martínez,",
        "apellido": "Thiago",
        "piloto": "Martínez, Thiago",
        "marca": "Ford",
        "vueltas": "20",
        "tiempo": "38:46.614",
        "diferencia": "27.495",
        "nacionalidad": "Martínez, Thiago"
      },
      {
        "pos": "20°",
        "nro": "71",
        "nombre": "Calvani,",
        "apellido": "Lucio",
        "piloto": "Calvani, Lucio",
        "marca": "Dodge",
        "vueltas": "20",
        "tiempo": "38:51.888",
        "diferencia": "32.769",
        "nacionalidad": "Calvani, Lucio"
      },
      {
        "pos": "21°",
        "nro": "25",
        "nombre": "Cotignola,",
        "apellido": "Luciano",
        "piloto": "Cotignola, Luciano",
        "marca": "Torino",
        "vueltas": "20",
        "tiempo": "38:51.889",
        "diferencia": "32.769",
        "nacionalidad": "Cotignola, Luciano"
      },
      {
        "pos": "22°",
        "nro": "14",
        "nombre": "De",
        "apellido": "Brabandere,",
        "piloto": "De Brabandere, Agustín",
        "marca": "Ford",
        "vueltas": "20",
        "tiempo": "38:56.328",
        "diferencia": "37.209",
        "nacionalidad": "De Brabandere, Agustín"
      },
      {
        "pos": "23°",
        "nro": "11",
        "nombre": "Canapino,",
        "apellido": "Matías",
        "piloto": "Canapino, Matías",
        "marca": "Chevrolet",
        "vueltas": "19",
        "tiempo": "37:00.672",
        "diferencia": "1 VTA",
        "nacionalidad": "Canapino, Matías"
      },
      {
        "pos": "24°",
        "nro": "20",
        "nombre": "Teti,",
        "apellido": "Jerónimo",
        "piloto": "Teti, Jerónimo",
        "marca": "Torino",
        "vueltas": "15",
        "tiempo": "32:34.324",
        "diferencia": "5 VTAS",
        "nacionalidad": "Teti, Jerónimo"
      },
      {
        "pos": "25°",
        "nro": "123",
        "nombre": "Gonnet,",
        "apellido": "Gerónimo",
        "piloto": "Gonnet, Gerónimo",
        "marca": "Torino",
        "vueltas": "12",
        "tiempo": "24:50.405",
        "diferencia": "8 VTAS",
        "nacionalidad": "Gonnet, Gerónimo"
      },
      {
        "pos": "26°",
        "nro": "188",
        "nombre": "Jaime,",
        "apellido": "Alberto",
        "piloto": "Jaime, Alberto Daniel",
        "marca": "Dodge",
        "vueltas": "12",
        "tiempo": "24:52.010",
        "diferencia": "8 VTAS",
        "nacionalidad": "Jaime, Alberto Daniel"
      },
      {
        "pos": "27°",
        "nro": "27",
        "nombre": "Reynoso,",
        "apellido": "Sebastián",
        "piloto": "Reynoso, Sebastián",
        "marca": "Ford",
        "vueltas": "10",
        "tiempo": "24:50.850",
        "diferencia": "10 VTAS",
        "nacionalidad": "Reynoso, Sebastián"
      },
      {
        "pos": "28°",
        "nro": "9",
        "nombre": "Valle,",
        "apellido": "Lucas",
        "piloto": "Valle, Lucas",
        "marca": "Dodge",
        "vueltas": "8",
        "tiempo": "16:23.027",
        "diferencia": "12 VTAS",
        "nacionalidad": "Valle, Lucas"
      },
      {
        "pos": "29°",
        "nro": "131",
        "nombre": "Rasuk,",
        "apellido": "José",
        "piloto": "Rasuk, José",
        "marca": "Dodge",
        "vueltas": "5",
        "tiempo": "09:54.032",
        "diferencia": "15 VTAS",
        "nacionalidad": "Rasuk, José"
      },
      {
        "pos": "30°",
        "nro": "113",
        "nombre": "Lugón,",
        "apellido": "Rodrigo",
        "piloto": "Lugón, Rodrigo",
        "marca": "Ford",
        "vueltas": "4",
        "tiempo": "07:06.052",
        "diferencia": "16 VTAS",
        "nacionalidad": "Lugón, Rodrigo"
      },
      {
        "pos": "31°",
        "nro": "109",
        "nombre": "Leguizamón,",
        "apellido": "Baltazar",
        "piloto": "Leguizamón, Baltazar",
        "marca": "Dodge",
        "vueltas": "4",
        "tiempo": "08:02.849",
        "diferencia": "16 VTAS",
        "nacionalidad": "Leguizamón, Baltazar"
      },
      {
        "pos": "32°",
        "nro": "125",
        "nombre": "Beraldi,",
        "apellido": "Cristian",
        "piloto": "Beraldi, Cristian",
        "marca": "Ford",
        "vueltas": "3",
        "tiempo": "04:55.178",
        "diferencia": "17 VTAS",
        "nacionalidad": "Beraldi, Cristian"
      },
      {
        "pos": "33°",
        "nro": "159",
        "nombre": "Séfchek,",
        "apellido": "Blas",
        "piloto": "Séfchek, Blas",
        "marca": "Torino",
        "vueltas": "3",
        "tiempo": "04:57.240",
        "diferencia": "17 VTAS",
        "nacionalidad": "Séfchek, Blas"
      },
      {
        "pos": "34°",
        "nro": "133",
        "nombre": "Maceira,",
        "apellido": "Juan",
        "piloto": "Maceira, Juan Ignacio",
        "marca": "Ford",
        "vueltas": "0",
        "tiempo": "",
        "diferencia": "20 VTAS",
        "nacionalidad": "Maceira, Juan Ignacio"
      }
    ]
  },
  {
    "url": "https://actc.org.ar/v3/carrera-on-line-resultados.ajax.php?intIDCarrera=1513&intIDTanda=15",
    "resultado": [
      {
        "pos": "1°",
        "nro": "3",
        "nombre": "Olmedo,",
        "apellido": "Jeremías",
        "piloto": "Olmedo, Jeremías",
        "marca": "Ford",
        "vueltas": "20",
        "tiempo": "30:23.724",
        "diferencia": "",
        "nacionalidad": "Olmedo, Jeremías"
      },
      {
        "pos": "2°",
        "nro": "193",
        "nombre": "Castro,",
        "apellido": "Marcos",
        "piloto": "Castro, Marcos",
        "marca": "Ford",
        "vueltas": "20",
        "tiempo": "30:30.326",
        "diferencia": "6.602",
        "nacionalidad": "Castro, Marcos"
      },
      {
        "pos": "3°",
        "nro": "12",
        "nombre": "Moscardini,",
        "apellido": "Nicolás",
        "piloto": "Moscardini, Nicolás",
        "marca": "Ford",
        "vueltas": "20",
        "tiempo": "30:32.694",
        "diferencia": "8.970",
        "nacionalidad": "Moscardini, Nicolás"
      },
      {
        "pos": "4°",
        "nro": "119",
        "nombre": "Palazzo,",
        "apellido": "Hernán",
        "piloto": "Palazzo, Hernán",
        "marca": "Chevrolet",
        "vueltas": "20",
        "tiempo": "30:33.258",
        "diferencia": "9.534",
        "nacionalidad": "Palazzo, Hernán"
      },
      {
        "pos": "5°",
        "nro": "86",
        "nombre": "Faín,",
        "apellido": "Ignacio",
        "piloto": "Faín, Ignacio",
        "marca": "Torino",
        "vueltas": "20",
        "tiempo": "30:33.747",
        "diferencia": "10.023",
        "nacionalidad": "Faín, Ignacio"
      },
      {
        "pos": "6°",
        "nro": "25",
        "nombre": "Cotignola,",
        "apellido": "Luciano",
        "piloto": "Cotignola, Luciano",
        "marca": "Torino",
        "vueltas": "20",
        "tiempo": "30:34.217",
        "diferencia": "10.493",
        "nacionalidad": "Cotignola, Luciano"
      },
      {
        "pos": "7°",
        "nro": "178",
        "nombre": "Tomasello,",
        "apellido": "Juan",
        "piloto": "Tomasello, Juan Manuel",
        "marca": "Chevrolet",
        "vueltas": "20",
        "tiempo": "30:34.873",
        "diferencia": "11.149",
        "nacionalidad": "Tomasello, Juan Manuel"
      },
      {
        "pos": "8°",
        "nro": "8",
        "nombre": "Impiombato,",
        "apellido": "Nicolás",
        "piloto": "Impiombato, Nicolás",
        "marca": "Chevrolet",
        "vueltas": "20",
        "tiempo": "30:42.079",
        "diferencia": "18.355",
        "nacionalidad": "Impiombato, Nicolás"
      },
      {
        "pos": "9°",
        "nro": "14",
        "nombre": "De",
        "apellido": "Brabandere,",
        "piloto": "De Brabandere, Agustín",
        "marca": "Ford",
        "vueltas": "20",
        "tiempo": "30:42.447",
        "diferencia": "18.723",
        "nacionalidad": "De Brabandere, Agustín"
      },
      {
        "pos": "10°",
        "nro": "54",
        "nombre": "Ochoa,",
        "apellido": "Joaquín",
        "piloto": "Ochoa, Joaquín",
        "marca": "Dodge",
        "vueltas": "20",
        "tiempo": "30:43.980",
        "diferencia": "20.256",
        "nacionalidad": "Ochoa, Joaquín"
      },
      {
        "pos": "11°",
        "nro": "197",
        "nombre": "Scialchi,",
        "apellido": "Jeremías",
        "piloto": "Scialchi, Jeremías",
        "marca": "Torino",
        "vueltas": "20",
        "tiempo": "30:46.018",
        "diferencia": "22.294",
        "nacionalidad": "Scialchi, Jeremías"
      },
      {
        "pos": "12°",
        "nro": "131",
        "nombre": "Rasuk,",
        "apellido": "José",
        "piloto": "Rasuk, José",
        "marca": "Dodge",
        "vueltas": "20",
        "tiempo": "30:48.267",
        "diferencia": "24.543",
        "nacionalidad": "Rasuk, José"
      },
      {
        "pos": "13°",
        "nro": "10",
        "nombre": "Azar,",
        "apellido": "Diego",
        "piloto": "Azar, Diego",
        "marca": "Toyota",
        "vueltas": "20",
        "tiempo": "30:48.466",
        "diferencia": "24.742",
        "nacionalidad": "Azar, Diego"
      },
      {
        "pos": "14°",
        "nro": "137",
        "nombre": "Scoltore,",
        "apellido": "Juan",
        "piloto": "Scoltore, Juan",
        "marca": "Chevrolet",
        "vueltas": "20",
        "tiempo": "30:48.640",
        "diferencia": "24.916",
        "nacionalidad": "Scoltore, Juan"
      },
      {
        "pos": "15°",
        "nro": "140",
        "nombre": "Chansard,",
        "apellido": "Gaspar",
        "piloto": "Chansard, Gaspar",
        "marca": "Dodge",
        "vueltas": "20",
        "tiempo": "30:49.139",
        "diferencia": "25.415",
        "nacionalidad": "Chansard, Gaspar"
      },
      {
        "pos": "16°",
        "nro": "23",
        "nombre": "Gandulia,",
        "apellido": "Gabriel",
        "piloto": "Gandulia, Gabriel",
        "marca": "Ford",
        "vueltas": "20",
        "tiempo": "30:49.871",
        "diferencia": "26.147",
        "nacionalidad": "Gandulia, Gabriel"
      },
      {
        "pos": "17°",
        "nro": "11",
        "nombre": "Canapino,",
        "apellido": "Matías",
        "piloto": "Canapino, Matías",
        "marca": "Chevrolet",
        "vueltas": "20",
        "tiempo": "30:50.300",
        "diferencia": "26.576",
        "nacionalidad": "Canapino, Matías"
      },
      {
        "pos": "18°",
        "nro": "20",
        "nombre": "Teti,",
        "apellido": "Jerónimo",
        "piloto": "Teti, Jerónimo",
        "marca": "Torino",
        "vueltas": "20",
        "tiempo": "30:55.957",
        "diferencia": "32.233",
        "nacionalidad": "Teti, Jerónimo"
      },
      {
        "pos": "19°",
        "nro": "133",
        "nombre": "Maceira,",
        "apellido": "Juan",
        "piloto": "Maceira, Juan Ignacio",
        "marca": "Ford",
        "vueltas": "20",
        "tiempo": "31:00.782",
        "diferencia": "37.058",
        "nacionalidad": "Maceira, Juan Ignacio"
      },
      {
        "pos": "20°",
        "nro": "113",
        "nombre": "Lugón,",
        "apellido": "Rodrigo",
        "piloto": "Lugón, Rodrigo",
        "marca": "Ford",
        "vueltas": "20",
        "tiempo": "31:01.004",
        "diferencia": "37.280",
        "nacionalidad": "Lugón, Rodrigo"
      },
      {
        "pos": "21°",
        "nro": "9",
        "nombre": "Valle,",
        "apellido": "Lucas",
        "piloto": "Valle, Lucas",
        "marca": "Dodge",
        "vueltas": "20",
        "tiempo": "31:01.516",
        "diferencia": "37.792",
        "nacionalidad": "Valle, Lucas"
      },
      {
        "pos": "22°",
        "nro": "71",
        "nombre": "Calvani,",
        "apellido": "Lucio",
        "piloto": "Calvani, Lucio",
        "marca": "Dodge",
        "vueltas": "20",
        "tiempo": "31:09.729",
        "diferencia": "46.005",
        "nacionalidad": "Calvani, Lucio"
      },
      {
        "pos": "23°",
        "nro": "21",
        "nombre": "Pilo,",
        "apellido": "Juan",
        "piloto": "Pilo, Juan Pablo",
        "marca": "Ford",
        "vueltas": "20",
        "tiempo": "31:14.876",
        "diferencia": "51.152",
        "nacionalidad": "Pilo, Juan Pablo"
      },
      {
        "pos": "24°",
        "nro": "117",
        "nombre": "Abdala,",
        "apellido": "Tomás",
        "piloto": "Abdala, Tomás",
        "marca": "Ford",
        "vueltas": "20",
        "tiempo": "31:15.607",
        "diferencia": "51.883",
        "nacionalidad": "Abdala, Tomás"
      },
      {
        "pos": "25°",
        "nro": "32",
        "nombre": "Markel,",
        "apellido": "Damián",
        "piloto": "Markel, Damián",
        "marca": "Ford",
        "vueltas": "20",
        "tiempo": "31:21.267",
        "diferencia": "57.543",
        "nacionalidad": "Markel, Damián"
      },
      {
        "pos": "26°",
        "nro": "27",
        "nombre": "Reynoso,",
        "apellido": "Sebastián",
        "piloto": "Reynoso, Sebastián",
        "marca": "Ford",
        "vueltas": "20",
        "tiempo": "31:32.993",
        "diferencia": "1:09.269",
        "nacionalidad": "Reynoso, Sebastián"
      },
      {
        "pos": "27°",
        "nro": "51",
        "nombre": "Ricciardi,",
        "apellido": "Thomas",
        "piloto": "Ricciardi, Thomas",
        "marca": "Ford",
        "vueltas": "20",
        "tiempo": "31:38.453",
        "diferencia": "1:14.729",
        "nacionalidad": "Ricciardi, Thomas"
      },
      {
        "pos": "28°",
        "nro": "109",
        "nombre": "Leguizamón,",
        "apellido": "Baltazar",
        "piloto": "Leguizamón, Baltazar",
        "marca": "Dodge",
        "vueltas": "19",
        "tiempo": "30:24.973",
        "diferencia": "1 VTA",
        "nacionalidad": "Leguizamón, Baltazar"
      },
      {
        "pos": "29°",
        "nro": "188",
        "nombre": "Jaime,",
        "apellido": "Alberto",
        "piloto": "Jaime, Alberto Daniel",
        "marca": "Dodge",
        "vueltas": "18",
        "tiempo": "28:58.603",
        "diferencia": "2 VTAS",
        "nacionalidad": "Jaime, Alberto Daniel"
      },
      {
        "pos": "30°",
        "nro": "152",
        "nombre": "Martínez,",
        "apellido": "Thiago",
        "piloto": "Martínez, Thiago",
        "marca": "Ford",
        "vueltas": "18",
        "tiempo": "31:16.658",
        "diferencia": "2 VTAS",
        "nacionalidad": "Martínez, Thiago"
      },
      {
        "pos": "31°",
        "nro": "118",
        "nombre": "Salse,",
        "apellido": "Sebastián",
        "piloto": "Salse, Sebastián",
        "marca": "Dodge",
        "vueltas": "16",
        "tiempo": "24:54.092",
        "diferencia": "4 VTAS",
        "nacionalidad": "Salse, Sebastián"
      },
      {
        "pos": "32°",
        "nro": "125",
        "nombre": "Beraldi,",
        "apellido": "Cristian",
        "piloto": "Beraldi, Cristian",
        "marca": "Ford",
        "vueltas": "4",
        "tiempo": "06:26.311",
        "diferencia": "16 VTAS",
        "nacionalidad": "Beraldi, Cristian"
      },
      {
        "pos": "33°",
        "nro": "123",
        "nombre": "Gonnet,",
        "apellido": "Gerónimo",
        "piloto": "Gonnet, Gerónimo",
        "marca": "Torino",
        "vueltas": "2",
        "tiempo": "03:08.847",
        "diferencia": "18 VTAS",
        "nacionalidad": "Gonnet, Gerónimo"
      },
      {
        "pos": "34°",
        "nro": "41",
        "nombre": "Barrio,",
        "apellido": "Jorge",
        "piloto": "Barrio, Jorge",
        "marca": "Chevrolet",
        "vueltas": "2",
        "tiempo": "03:09.993",
        "diferencia": "18 VTAS",
        "nacionalidad": "Barrio, Jorge"
      }
    ]
  },
  {
    "url": "https://actc.org.ar/v3/carrera-on-line-resultados.ajax.php?intIDCarrera=1514&intIDTanda=15",
    "resultado": [
      {
        "pos": "1°",
        "nro": "54",
        "nombre": "Ochoa,",
        "apellido": "Joaquín",
        "piloto": "Ochoa, Joaquín",
        "marca": "Dodge",
        "vueltas": "25",
        "tiempo": "32:06.795",
        "diferencia": "",
        "nacionalidad": "Ochoa, Joaquín"
      },
      {
        "pos": "2°",
        "nro": "178",
        "nombre": "Tomasello,",
        "apellido": "Juan",
        "piloto": "Tomasello, Juan Manuel",
        "marca": "CHEVROLET",
        "vueltas": "25",
        "tiempo": "32:08.404",
        "diferencia": "1.609",
        "nacionalidad": "Tomasello, Juan Manuel"
      },
      {
        "pos": "3°",
        "nro": "117",
        "nombre": "Abdala,",
        "apellido": "Tomás",
        "piloto": "Abdala, Tomás",
        "marca": "Ford",
        "vueltas": "25",
        "tiempo": "32:09.097",
        "diferencia": "2.302",
        "nacionalidad": "Abdala, Tomás"
      },
      {
        "pos": "4°",
        "nro": "12",
        "nombre": "Moscardini,",
        "apellido": "Nicolás",
        "piloto": "Moscardini, Nicolás",
        "marca": "Ford",
        "vueltas": "25",
        "tiempo": "32:18.457",
        "diferencia": "11.662",
        "nacionalidad": "Moscardini, Nicolás"
      },
      {
        "pos": "5°",
        "nro": "119",
        "nombre": "Palazzo,",
        "apellido": "Hernán",
        "piloto": "Palazzo, Hernán",
        "marca": "CHEVROLET",
        "vueltas": "25",
        "tiempo": "32:18.720",
        "diferencia": "11.925",
        "nacionalidad": "Palazzo, Hernán"
      },
      {
        "pos": "6°",
        "nro": "10",
        "nombre": "Azar,",
        "apellido": "Diego",
        "piloto": "Azar, Diego",
        "marca": "Toyota",
        "vueltas": "25",
        "tiempo": "32:19.191",
        "diferencia": "12.396",
        "nacionalidad": "Azar, Diego"
      },
      {
        "pos": "7°",
        "nro": "193",
        "nombre": "Castro,",
        "apellido": "Marcos",
        "piloto": "Castro, Marcos",
        "marca": "Ford",
        "vueltas": "25",
        "tiempo": "32:19.965",
        "diferencia": "13.170",
        "nacionalidad": "Castro, Marcos"
      },
      {
        "pos": "8°",
        "nro": "3",
        "nombre": "Olmedo,",
        "apellido": "Jeremías",
        "piloto": "Olmedo, Jeremías",
        "marca": "Ford",
        "vueltas": "25",
        "tiempo": "32:22.059",
        "diferencia": "15.264",
        "nacionalidad": "Olmedo, Jeremías"
      },
      {
        "pos": "9°",
        "nro": "137",
        "nombre": "Scoltore,",
        "apellido": "Juan",
        "piloto": "Scoltore, Juan",
        "marca": "CHEVROLET",
        "vueltas": "25",
        "tiempo": "32:26.161",
        "diferencia": "19.366",
        "nacionalidad": "Scoltore, Juan"
      },
      {
        "pos": "10°",
        "nro": "8",
        "nombre": "Impiombato,",
        "apellido": "Nicolás",
        "piloto": "Impiombato, Nicolás",
        "marca": "CHEVROLET",
        "vueltas": "25",
        "tiempo": "32:27.600",
        "diferencia": "20.805",
        "nacionalidad": "Impiombato, Nicolás"
      },
      {
        "pos": "11°",
        "nro": "25",
        "nombre": "Cotignola,",
        "apellido": "Luciano",
        "piloto": "Cotignola, Luciano",
        "marca": "Torino",
        "vueltas": "25",
        "tiempo": "32:28.373",
        "diferencia": "21.578",
        "nacionalidad": "Cotignola, Luciano"
      },
      {
        "pos": "12°",
        "nro": "51",
        "nombre": "Ricciardi,",
        "apellido": "Thomas",
        "piloto": "Ricciardi, Thomas",
        "marca": "Ford",
        "vueltas": "25",
        "tiempo": "32:30.162",
        "diferencia": "23.367",
        "nacionalidad": "Ricciardi, Thomas"
      },
      {
        "pos": "13°",
        "nro": "32",
        "nombre": "Markel,",
        "apellido": "Damián",
        "piloto": "Markel, Damián",
        "marca": "Ford",
        "vueltas": "25",
        "tiempo": "32:34.833",
        "diferencia": "28.038",
        "nacionalidad": "Markel, Damián"
      },
      {
        "pos": "14°",
        "nro": "131",
        "nombre": "Rasuk,",
        "apellido": "José",
        "piloto": "Rasuk, José",
        "marca": "Dodge",
        "vueltas": "25",
        "tiempo": "32:35.730",
        "diferencia": "28.935",
        "nacionalidad": "Rasuk, José"
      },
      {
        "pos": "15°",
        "nro": "41",
        "nombre": "Barrio,",
        "apellido": "Jorge",
        "piloto": "Barrio, Jorge",
        "marca": "CHEVROLET",
        "vueltas": "25",
        "tiempo": "32:36.131",
        "diferencia": "29.336",
        "nacionalidad": "Barrio, Jorge"
      },
      {
        "pos": "16°",
        "nro": "11",
        "nombre": "Canapino,",
        "apellido": "Matías",
        "piloto": "Canapino, Matías",
        "marca": "CHEVROLET",
        "vueltas": "25",
        "tiempo": "32:36.307",
        "diferencia": "29.512",
        "nacionalidad": "Canapino, Matías"
      },
      {
        "pos": "17°",
        "nro": "123",
        "nombre": "Gonnet,",
        "apellido": "Gerónimo",
        "piloto": "Gonnet, Gerónimo",
        "marca": "Torino",
        "vueltas": "25",
        "tiempo": "32:36.448",
        "diferencia": "29.653",
        "nacionalidad": "Gonnet, Gerónimo"
      },
      {
        "pos": "18°",
        "nro": "71",
        "nombre": "Calvani,",
        "apellido": "Lucio",
        "piloto": "Calvani, Lucio",
        "marca": "Dodge",
        "vueltas": "25",
        "tiempo": "32:48.633",
        "diferencia": "41.838",
        "nacionalidad": "Calvani, Lucio"
      },
      {
        "pos": "19°",
        "nro": "20",
        "nombre": "Teti,",
        "apellido": "Jerónimo",
        "piloto": "Teti, Jerónimo",
        "marca": "Torino",
        "vueltas": "25",
        "tiempo": "32:49.598",
        "diferencia": "42.803",
        "nacionalidad": "Teti, Jerónimo"
      },
      {
        "pos": "20°",
        "nro": "125",
        "nombre": "Beraldi,",
        "apellido": "Cristian",
        "piloto": "Beraldi, Cristian",
        "marca": "Ford",
        "vueltas": "25",
        "tiempo": "32:51.651",
        "diferencia": "44.856",
        "nacionalidad": "Beraldi, Cristian"
      },
      {
        "pos": "21°",
        "nro": "140",
        "nombre": "Chansard,",
        "apellido": "Gaspar",
        "piloto": "Chansard, Gaspar",
        "marca": "Dodge",
        "vueltas": "25",
        "tiempo": "32:52.939",
        "diferencia": "46.144",
        "nacionalidad": "Chansard, Gaspar"
      },
      {
        "pos": "22°",
        "nro": "27",
        "nombre": "Reynoso,",
        "apellido": "Sebastián",
        "piloto": "Reynoso, Sebastián",
        "marca": "Ford",
        "vueltas": "25",
        "tiempo": "33:09.192",
        "diferencia": "1:02.397",
        "nacionalidad": "Reynoso, Sebastián"
      },
      {
        "pos": "23°",
        "nro": "188",
        "nombre": "Jaime,",
        "apellido": "Alberto",
        "piloto": "Jaime, Alberto Daniel",
        "marca": "Dodge",
        "vueltas": "25",
        "tiempo": "33:21.265",
        "diferencia": "1:14.470",
        "nacionalidad": "Jaime, Alberto Daniel"
      },
      {
        "pos": "24°",
        "nro": "118",
        "nombre": "Salse,",
        "apellido": "Sebastián",
        "piloto": "Salse, Sebastián",
        "marca": "Dodge",
        "vueltas": "24",
        "tiempo": "32:45.286",
        "diferencia": "1 VTA",
        "nacionalidad": "Salse, Sebastián"
      },
      {
        "pos": "25°",
        "nro": "197",
        "nombre": "Scialchi,",
        "apellido": "Jeremías",
        "piloto": "Scialchi, Jeremías",
        "marca": "Torino",
        "vueltas": "24",
        "tiempo": "32:54.445",
        "diferencia": "1 VTA",
        "nacionalidad": "Scialchi, Jeremías"
      },
      {
        "pos": "26°",
        "nro": "86",
        "nombre": "Faín,",
        "apellido": "Ignacio",
        "piloto": "Faín, Ignacio",
        "marca": "Torino",
        "vueltas": "24",
        "tiempo": "33:02.550",
        "diferencia": "1 VTA",
        "nacionalidad": "Faín, Ignacio"
      },
      {
        "pos": "27°",
        "nro": "23",
        "nombre": "Gandulia,",
        "apellido": "Gabriel",
        "piloto": "Gandulia, Gabriel",
        "marca": "Ford",
        "vueltas": "24",
        "tiempo": "33:23.010",
        "diferencia": "1 VTA",
        "nacionalidad": "Gandulia, Gabriel"
      },
      {
        "pos": "28°",
        "nro": "95",
        "nombre": "Manta,",
        "apellido": "Javier",
        "piloto": "Manta, Javier",
        "marca": "CHEVROLET",
        "vueltas": "23",
        "tiempo": "33:13.892",
        "diferencia": "2 VTAS",
        "nacionalidad": "Manta, Javier"
      },
      {
        "pos": "29°",
        "nro": "109",
        "nombre": "Leguizamón,",
        "apellido": "Baltazar",
        "piloto": "Leguizamón, Baltazar",
        "marca": "Dodge",
        "vueltas": "19",
        "tiempo": "25:30.436",
        "diferencia": "6 VTAS",
        "nacionalidad": "Leguizamón, Baltazar"
      },
      {
        "pos": "30°",
        "nro": "9",
        "nombre": "Valle,",
        "apellido": "Lucas",
        "piloto": "Valle, Lucas",
        "marca": "Dodge",
        "vueltas": "16",
        "tiempo": "23:02.955",
        "diferencia": "9 VTAS",
        "nacionalidad": "Valle, Lucas"
      },
      {
        "pos": "31°",
        "nro": "101",
        "nombre": "Weimann,",
        "apellido": "Alejandro",
        "piloto": "Weimann, Alejandro",
        "marca": "Dodge",
        "vueltas": "14",
        "tiempo": "20:30.200",
        "diferencia": "11 VTAS",
        "nacionalidad": "Weimann, Alejandro"
      },
      {
        "pos": "32°",
        "nro": "159",
        "nombre": "Séfchek,",
        "apellido": "Blas",
        "piloto": "Séfchek, Blas",
        "marca": "Torino",
        "vueltas": "12",
        "tiempo": "15:50.690",
        "diferencia": "13 VTAS",
        "nacionalidad": "Séfchek, Blas"
      },
      {
        "pos": "33°",
        "nro": "14",
        "nombre": "De",
        "apellido": "Brabandere,",
        "piloto": "De Brabandere, Agustín",
        "marca": "Ford",
        "vueltas": "8",
        "tiempo": "10:15.088",
        "diferencia": "17 VTAS",
        "nacionalidad": "De Brabandere, Agustín"
      },
      {
        "pos": "34°",
        "nro": "21",
        "nombre": "Pilo,",
        "apellido": "Juan",
        "piloto": "Pilo, Juan Pablo",
        "marca": "Ford",
        "vueltas": "5",
        "tiempo": "06:58.130",
        "diferencia": "20 VTAS",
        "nacionalidad": "Pilo, Juan Pablo"
      },
      {
        "pos": "35°",
        "nro": "152",
        "nombre": "Martínez,",
        "apellido": "Thiago",
        "piloto": "Martínez, Thiago",
        "marca": "Ford",
        "vueltas": "3",
        "tiempo": "03:56.693",
        "diferencia": "22 VTAS",
        "nacionalidad": "Martínez, Thiago"
      }
    ]
  },
  {
    "url": "https://actc.org.ar/v3/carrera-on-line-resultados.ajax.php?intIDCarrera=1515&intIDTanda=15",
    "resultado": [
      {
        "pos": "1°",
        "nro": "9",
        "nombre": "Valle,",
        "apellido": "Lucas",
        "piloto": "Valle, Lucas",
        "marca": "Dodge",
        "vueltas": "20",
        "tiempo": "38:36.642",
        "diferencia": "",
        "nacionalidad": "Valle, Lucas"
      },
      {
        "pos": "2°",
        "nro": "41",
        "nombre": "Barrio,",
        "apellido": "Jorge",
        "piloto": "Barrio, Jorge",
        "marca": "CHEVROLET",
        "vueltas": "20",
        "tiempo": "38:40.091",
        "diferencia": "3.449",
        "nacionalidad": "Barrio, Jorge"
      },
      {
        "pos": "3°",
        "nro": "197",
        "nombre": "Scialchi,",
        "apellido": "Jeremías",
        "piloto": "Scialchi, Jeremías",
        "marca": "Torino",
        "vueltas": "20",
        "tiempo": "38:40.582",
        "diferencia": "3.940",
        "nacionalidad": "Scialchi, Jeremías"
      },
      {
        "pos": "4°",
        "nro": "131",
        "nombre": "Rasuk,",
        "apellido": "José",
        "piloto": "Rasuk, José",
        "marca": "Dodge",
        "vueltas": "20",
        "tiempo": "38:52.021",
        "diferencia": "15.379",
        "nacionalidad": "Rasuk, José"
      },
      {
        "pos": "5°",
        "nro": "118",
        "nombre": "Salse,",
        "apellido": "Sebastián",
        "piloto": "Salse, Sebastián",
        "marca": "Dodge",
        "vueltas": "20",
        "tiempo": "38:52.483",
        "diferencia": "15.841",
        "nacionalidad": "Salse, Sebastián"
      },
      {
        "pos": "6°",
        "nro": "119",
        "nombre": "Palazzo,",
        "apellido": "Hernán",
        "piloto": "Palazzo, Hernán",
        "marca": "CHEVROLET",
        "vueltas": "20",
        "tiempo": "38:53.529",
        "diferencia": "16.887",
        "nacionalidad": "Palazzo, Hernán"
      },
      {
        "pos": "7°",
        "nro": "109",
        "nombre": "Leguizamón,",
        "apellido": "Baltazar",
        "piloto": "Leguizamón, Baltazar",
        "marca": "Dodge",
        "vueltas": "20",
        "tiempo": "38:54.102",
        "diferencia": "17.460",
        "nacionalidad": "Leguizamón, Baltazar"
      },
      {
        "pos": "8°",
        "nro": "113",
        "nombre": "Lugón,",
        "apellido": "Rodrigo",
        "piloto": "Lugón, Rodrigo",
        "marca": "Ford",
        "vueltas": "20",
        "tiempo": "38:54.407",
        "diferencia": "17.765",
        "nacionalidad": "Lugón, Rodrigo"
      },
      {
        "pos": "9°",
        "nro": "21",
        "nombre": "Pilo,",
        "apellido": "Juan",
        "piloto": "Pilo, Juan Pablo",
        "marca": "Ford",
        "vueltas": "20",
        "tiempo": "38:57.190",
        "diferencia": "20.548",
        "nacionalidad": "Pilo, Juan Pablo"
      },
      {
        "pos": "10°",
        "nro": "193",
        "nombre": "Castro,",
        "apellido": "Marcos",
        "piloto": "Castro, Marcos",
        "marca": "Ford",
        "vueltas": "20",
        "tiempo": "38:59.631",
        "diferencia": "22.989",
        "nacionalidad": "Castro, Marcos"
      },
      {
        "pos": "11°",
        "nro": "71",
        "nombre": "Calvani,",
        "apellido": "Lucio",
        "piloto": "Calvani, Lucio",
        "marca": "Dodge",
        "vueltas": "20",
        "tiempo": "39:02.460",
        "diferencia": "25.818",
        "nacionalidad": "Calvani, Lucio"
      },
      {
        "pos": "12°",
        "nro": "54",
        "nombre": "Ochoa,",
        "apellido": "Joaquín",
        "piloto": "Ochoa, Joaquín",
        "marca": "Dodge",
        "vueltas": "20",
        "tiempo": "39:03.018",
        "diferencia": "26.376",
        "nacionalidad": "Ochoa, Joaquín"
      },
      {
        "pos": "13°",
        "nro": "123",
        "nombre": "Gonnet,",
        "apellido": "Gerónimo",
        "piloto": "Gonnet, Gerónimo",
        "marca": "Torino",
        "vueltas": "20",
        "tiempo": "39:05.660",
        "diferencia": "29.018",
        "nacionalidad": "Gonnet, Gerónimo"
      },
      {
        "pos": "14°",
        "nro": "8",
        "nombre": "Impiombato,",
        "apellido": "Nicolás",
        "piloto": "Impiombato, Nicolás",
        "marca": "CHEVROLET",
        "vueltas": "20",
        "tiempo": "39:07.360",
        "diferencia": "30.718",
        "nacionalidad": "Impiombato, Nicolás"
      },
      {
        "pos": "15°",
        "nro": "27",
        "nombre": "Reynoso,",
        "apellido": "Sebastián",
        "piloto": "Reynoso, Sebastián",
        "marca": "Ford",
        "vueltas": "20",
        "tiempo": "39:07.598",
        "diferencia": "30.956",
        "nacionalidad": "Reynoso, Sebastián"
      },
      {
        "pos": "16°",
        "nro": "117",
        "nombre": "Abdala,",
        "apellido": "Tomás",
        "piloto": "Abdala, Tomás",
        "marca": "Ford",
        "vueltas": "20",
        "tiempo": "39:08.170",
        "diferencia": "31.528",
        "nacionalidad": "Abdala, Tomás"
      },
      {
        "pos": "17°",
        "nro": "23",
        "nombre": "Gandulia,",
        "apellido": "Gabriel",
        "piloto": "Gandulia, Gabriel",
        "marca": "Ford",
        "vueltas": "20",
        "tiempo": "39:08.461",
        "diferencia": "31.819",
        "nacionalidad": "Gandulia, Gabriel"
      },
      {
        "pos": "18°",
        "nro": "178",
        "nombre": "Tomasello,",
        "apellido": "Juan",
        "piloto": "Tomasello, Juan Manuel",
        "marca": "CHEVROLET",
        "vueltas": "20",
        "tiempo": "39:09.651",
        "diferencia": "33.009",
        "nacionalidad": "Tomasello, Juan Manuel"
      },
      {
        "pos": "19°",
        "nro": "51",
        "nombre": "Ricciardi,",
        "apellido": "Thomas",
        "piloto": "Ricciardi, Thomas",
        "marca": "Ford",
        "vueltas": "20",
        "tiempo": "39:10.836",
        "diferencia": "34.194",
        "nacionalidad": "Ricciardi, Thomas"
      },
      {
        "pos": "20°",
        "nro": "137",
        "nombre": "Scoltore,",
        "apellido": "Juan",
        "piloto": "Scoltore, Juan",
        "marca": "CHEVROLET",
        "vueltas": "20",
        "tiempo": "39:11.162",
        "diferencia": "34.520",
        "nacionalidad": "Scoltore, Juan"
      },
      {
        "pos": "21°",
        "nro": "86",
        "nombre": "Faín,",
        "apellido": "Ignacio",
        "piloto": "Faín, Ignacio",
        "marca": "Torino",
        "vueltas": "20",
        "tiempo": "39:11.352",
        "diferencia": "34.710",
        "nacionalidad": "Faín, Ignacio"
      },
      {
        "pos": "22°",
        "nro": "20",
        "nombre": "Teti,",
        "apellido": "Jerónimo",
        "piloto": "Teti, Jerónimo",
        "marca": "Torino",
        "vueltas": "20",
        "tiempo": "39:11.850",
        "diferencia": "35.208",
        "nacionalidad": "Teti, Jerónimo"
      },
      {
        "pos": "23°",
        "nro": "14",
        "nombre": "De",
        "apellido": "Brabandere,",
        "piloto": "De Brabandere, Agustín",
        "marca": "Ford",
        "vueltas": "20",
        "tiempo": "39:12.773",
        "diferencia": "36.131",
        "nacionalidad": "De Brabandere, Agustín"
      },
      {
        "pos": "24°",
        "nro": "188",
        "nombre": "Jaime,",
        "apellido": "Alberto",
        "piloto": "Jaime, Alberto Daniel",
        "marca": "Dodge",
        "vueltas": "20",
        "tiempo": "39:21.067",
        "diferencia": "44.425",
        "nacionalidad": "Jaime, Alberto Daniel"
      },
      {
        "pos": "25°",
        "nro": "140",
        "nombre": "Chansard,",
        "apellido": "Gaspar",
        "piloto": "Chansard, Gaspar",
        "marca": "Dodge",
        "vueltas": "20",
        "tiempo": "39:35.851",
        "diferencia": "59.209",
        "nacionalidad": "Chansard, Gaspar"
      },
      {
        "pos": "26°",
        "nro": "3",
        "nombre": "Olmedo,",
        "apellido": "Jeremías",
        "piloto": "Olmedo, Jeremías",
        "marca": "Ford",
        "vueltas": "20",
        "tiempo": "40:02.928",
        "diferencia": "1:26.286",
        "nacionalidad": "Olmedo, Jeremías"
      },
      {
        "pos": "27°",
        "nro": "25",
        "nombre": "Cotignola,",
        "apellido": "Luciano",
        "piloto": "Cotignola, Luciano",
        "marca": "Torino",
        "vueltas": "18",
        "tiempo": "35:41.573",
        "diferencia": "2 VTAS",
        "nacionalidad": "Cotignola, Luciano"
      },
      {
        "pos": "28°",
        "nro": "125",
        "nombre": "Beraldi,",
        "apellido": "Cristian",
        "piloto": "Beraldi, Cristian",
        "marca": "Ford",
        "vueltas": "18",
        "tiempo": "36:37.168",
        "diferencia": "2 VTAS",
        "nacionalidad": "Beraldi, Cristian"
      },
      {
        "pos": "29°",
        "nro": "11",
        "nombre": "Canapino,",
        "apellido": "Matías",
        "piloto": "Canapino, Matías",
        "marca": "CHEVROLET",
        "vueltas": "14",
        "tiempo": "27:59.633",
        "diferencia": "6 VTAS",
        "nacionalidad": "Canapino, Matías"
      },
      {
        "pos": "30°",
        "nro": "10",
        "nombre": "Azar,",
        "apellido": "Diego",
        "piloto": "Azar, Diego",
        "marca": "Toyota",
        "vueltas": "11",
        "tiempo": "21:49.896",
        "diferencia": "9 VTAS",
        "nacionalidad": "Azar, Diego"
      },
      {
        "pos": "31°",
        "nro": "133",
        "nombre": "Maceira,",
        "apellido": "Juan",
        "piloto": "Maceira, Juan Ignacio",
        "marca": "Ford",
        "vueltas": "5",
        "tiempo": "13:26.995",
        "diferencia": "15 VTAS",
        "nacionalidad": "Maceira, Juan Ignacio"
      },
      {
        "pos": "32°",
        "nro": "12",
        "nombre": "Moscardini,",
        "apellido": "Nicolás",
        "piloto": "Moscardini, Nicolás",
        "marca": "Ford",
        "vueltas": "3",
        "tiempo": "06:03.589",
        "diferencia": "17 VTAS",
        "nacionalidad": "Moscardini, Nicolás"
      }
    ]
  },
  {
    "url": "https://actc.org.ar/v3/carrera-on-line-resultados.ajax.php?intIDCarrera=1516&intIDTanda=15",
    "resultado": [
      {
        "pos": "1°",
        "nro": "11",
        "nombre": "Canapino,",
        "apellido": "Matías",
        "piloto": "Canapino, Matías",
        "marca": "CHEVROLET",
        "vueltas": "20",
        "tiempo": "34:29.470",
        "diferencia": "",
        "nacionalidad": "Canapino, Matías"
      },
      {
        "pos": "2°",
        "nro": "12",
        "nombre": "Moscardini,",
        "apellido": "Nicolás",
        "piloto": "Moscardini, Nicolás",
        "marca": "Ford",
        "vueltas": "20",
        "tiempo": "34:29.938",
        "diferencia": "0.468",
        "nacionalidad": "Moscardini, Nicolás"
      },
      {
        "pos": "3°",
        "nro": "113",
        "nombre": "Lugón,",
        "apellido": "Rodrigo",
        "piloto": "Lugón, Rodrigo",
        "marca": "Ford",
        "vueltas": "20",
        "tiempo": "34:32.587",
        "diferencia": "3.117",
        "nacionalidad": "Lugón, Rodrigo"
      },
      {
        "pos": "4°",
        "nro": "10",
        "nombre": "Azar,",
        "apellido": "Diego",
        "piloto": "Azar, Diego",
        "marca": "Toyota",
        "vueltas": "20",
        "tiempo": "34:33.004",
        "diferencia": "3.534",
        "nacionalidad": "Azar, Diego"
      },
      {
        "pos": "5°",
        "nro": "119",
        "nombre": "Palazzo,",
        "apellido": "Hernán",
        "piloto": "Palazzo, Hernán",
        "marca": "CHEVROLET",
        "vueltas": "20",
        "tiempo": "34:33.387",
        "diferencia": "3.917",
        "nacionalidad": "Palazzo, Hernán"
      },
      {
        "pos": "6°",
        "nro": "3",
        "nombre": "Olmedo,",
        "apellido": "Jeremías",
        "piloto": "Olmedo, Jeremías",
        "marca": "Ford",
        "vueltas": "20",
        "tiempo": "34:35.076",
        "diferencia": "5.606",
        "nacionalidad": "Olmedo, Jeremías"
      },
      {
        "pos": "7°",
        "nro": "23",
        "nombre": "Gandulia,",
        "apellido": "Gabriel",
        "piloto": "Gandulia, Gabriel",
        "marca": "Ford",
        "vueltas": "20",
        "tiempo": "34:37.755",
        "diferencia": "8.285",
        "nacionalidad": "Gandulia, Gabriel"
      },
      {
        "pos": "8°",
        "nro": "14",
        "nombre": "De",
        "apellido": "Brabandere,",
        "piloto": "De Brabandere, Agustín",
        "marca": "Ford",
        "vueltas": "20",
        "tiempo": "34:39.158",
        "diferencia": "9.688",
        "nacionalidad": "De Brabandere, Agustín"
      },
      {
        "pos": "9°",
        "nro": "8",
        "nombre": "Impiombato,",
        "apellido": "Nicolás",
        "piloto": "Impiombato, Nicolás",
        "marca": "CHEVROLET",
        "vueltas": "20",
        "tiempo": "34:39.635",
        "diferencia": "10.165",
        "nacionalidad": "Impiombato, Nicolás"
      },
      {
        "pos": "10°",
        "nro": "193",
        "nombre": "Castro,",
        "apellido": "Marcos",
        "piloto": "Castro, Marcos",
        "marca": "Ford",
        "vueltas": "20",
        "tiempo": "34:39.636",
        "diferencia": "10.166",
        "nacionalidad": "Castro, Marcos"
      },
      {
        "pos": "11°",
        "nro": "197",
        "nombre": "Scialchi,",
        "apellido": "Jeremías",
        "piloto": "Scialchi, Jeremías",
        "marca": "Torino",
        "vueltas": "20",
        "tiempo": "34:39.926",
        "diferencia": "10.456",
        "nacionalidad": "Scialchi, Jeremías"
      },
      {
        "pos": "12°",
        "nro": "9",
        "nombre": "Valle,",
        "apellido": "Lucas",
        "piloto": "Valle, Lucas",
        "marca": "Dodge",
        "vueltas": "20",
        "tiempo": "34:43.275",
        "diferencia": "13.805",
        "nacionalidad": "Valle, Lucas"
      },
      {
        "pos": "13°",
        "nro": "51",
        "nombre": "Ricciardi,",
        "apellido": "Thomas",
        "piloto": "Ricciardi, Thomas",
        "marca": "Ford",
        "vueltas": "20",
        "tiempo": "34:51.625",
        "diferencia": "22.155",
        "nacionalidad": "Ricciardi, Thomas"
      },
      {
        "pos": "14°",
        "nro": "25",
        "nombre": "Cotignola,",
        "apellido": "Luciano",
        "piloto": "Cotignola, Luciano",
        "marca": "Torino",
        "vueltas": "20",
        "tiempo": "34:51.788",
        "diferencia": "22.318",
        "nacionalidad": "Cotignola, Luciano"
      },
      {
        "pos": "15°",
        "nro": "178",
        "nombre": "Tomasello,",
        "apellido": "Juan",
        "piloto": "Tomasello, Juan Manuel",
        "marca": "CHEVROLET",
        "vueltas": "20",
        "tiempo": "34:52.350",
        "diferencia": "22.880",
        "nacionalidad": "Tomasello, Juan Manuel"
      },
      {
        "pos": "16°",
        "nro": "20",
        "nombre": "Teti,",
        "apellido": "Jerónimo",
        "piloto": "Teti, Jerónimo",
        "marca": "Torino",
        "vueltas": "20",
        "tiempo": "34:52.417",
        "diferencia": "22.947",
        "nacionalidad": "Teti, Jerónimo"
      },
      {
        "pos": "17°",
        "nro": "41",
        "nombre": "Barrio,",
        "apellido": "Jorge",
        "piloto": "Barrio, Jorge",
        "marca": "CHEVROLET",
        "vueltas": "20",
        "tiempo": "34:56.729",
        "diferencia": "27.259",
        "nacionalidad": "Barrio, Jorge"
      },
      {
        "pos": "18°",
        "nro": "32",
        "nombre": "Markel,",
        "apellido": "Damián",
        "piloto": "Markel, Damián",
        "marca": "Dodge",
        "vueltas": "20",
        "tiempo": "35:00.395",
        "diferencia": "30.925",
        "nacionalidad": "Markel, Damián"
      },
      {
        "pos": "19°",
        "nro": "71",
        "nombre": "Calvani,",
        "apellido": "Lucio",
        "piloto": "Calvani, Lucio",
        "marca": "Dodge",
        "vueltas": "20",
        "tiempo": "35:00.662",
        "diferencia": "31.192",
        "nacionalidad": "Calvani, Lucio"
      },
      {
        "pos": "20°",
        "nro": "118",
        "nombre": "Salse,",
        "apellido": "Sebastián",
        "piloto": "Salse, Sebastián",
        "marca": "Dodge",
        "vueltas": "20",
        "tiempo": "35:03.746",
        "diferencia": "34.276",
        "nacionalidad": "Salse, Sebastián"
      },
      {
        "pos": "21°",
        "nro": "125",
        "nombre": "Beraldi,",
        "apellido": "Cristian",
        "piloto": "Beraldi, Cristian",
        "marca": "Ford",
        "vueltas": "20",
        "tiempo": "35:10.815",
        "diferencia": "41.345",
        "nacionalidad": "Beraldi, Cristian"
      },
      {
        "pos": "22°",
        "nro": "101",
        "nombre": "Weimann,",
        "apellido": "Alejandro",
        "piloto": "Weimann, Alejandro",
        "marca": "Dodge",
        "vueltas": "20",
        "tiempo": "35:18.592",
        "diferencia": "49.122",
        "nacionalidad": "Weimann, Alejandro"
      },
      {
        "pos": "23°",
        "nro": "133",
        "nombre": "Maceira,",
        "apellido": "Juan",
        "piloto": "Maceira, Juan Ignacio",
        "marca": "Ford",
        "vueltas": "19",
        "tiempo": "35:28.379",
        "diferencia": "1 VTA",
        "nacionalidad": "Maceira, Juan Ignacio"
      },
      {
        "pos": "24°",
        "nro": "54",
        "nombre": "Ochoa,",
        "apellido": "Joaquín",
        "piloto": "Ochoa, Joaquín",
        "marca": "Dodge",
        "vueltas": "18",
        "tiempo": "35:19.986",
        "diferencia": "2 VTAS",
        "nacionalidad": "Ochoa, Joaquín"
      },
      {
        "pos": "25°",
        "nro": "21",
        "nombre": "Pilo,",
        "apellido": "Juan",
        "piloto": "Pilo, Juan Pablo",
        "marca": "Ford",
        "vueltas": "16",
        "tiempo": "28:54.302",
        "diferencia": "4 VTAS",
        "nacionalidad": "Pilo, Juan Pablo"
      },
      {
        "pos": "26°",
        "nro": "27",
        "nombre": "Reynoso,",
        "apellido": "Sebastián",
        "piloto": "Reynoso, Sebastián",
        "marca": "Ford",
        "vueltas": "16",
        "tiempo": "28:54.730",
        "diferencia": "4 VTAS",
        "nacionalidad": "Reynoso, Sebastián"
      },
      {
        "pos": "27°",
        "nro": "86",
        "nombre": "Faín,",
        "apellido": "Ignacio",
        "piloto": "Faín, Ignacio",
        "marca": "Torino",
        "vueltas": "5",
        "tiempo": "10:53.323",
        "diferencia": "15 VTAS",
        "nacionalidad": "Faín, Ignacio"
      },
      {
        "pos": "28°",
        "nro": "188",
        "nombre": "Jaime,",
        "apellido": "Alberto",
        "piloto": "Jaime, Alberto Daniel",
        "marca": "Dodge",
        "vueltas": "5",
        "tiempo": "10:59.227",
        "diferencia": "15 VTAS",
        "nacionalidad": "Jaime, Alberto Daniel"
      },
      {
        "pos": "29°",
        "nro": "140",
        "nombre": "Chansard,",
        "apellido": "Gaspar",
        "piloto": "Chansard, Gaspar",
        "marca": "Dodge",
        "vueltas": "5",
        "tiempo": "11:05.901",
        "diferencia": "15 VTAS",
        "nacionalidad": "Chansard, Gaspar"
      },
      {
        "pos": "30°",
        "nro": "159",
        "nombre": "Séfchek,",
        "apellido": "Blas",
        "piloto": "Séfchek, Blas",
        "marca": "Torino",
        "vueltas": "4",
        "tiempo": "08:56.135",
        "diferencia": "16 VTAS",
        "nacionalidad": "Séfchek, Blas"
      },
      {
        "pos": "31°",
        "nro": "109",
        "nombre": "Leguizamón,",
        "apellido": "Baltazar",
        "piloto": "Leguizamón, Baltazar",
        "marca": "Dodge",
        "vueltas": "4",
        "tiempo": "08:57.337",
        "diferencia": "16 VTAS",
        "nacionalidad": "Leguizamón, Baltazar"
      },
      {
        "pos": "32°",
        "nro": "137",
        "nombre": "Scoltore,",
        "apellido": "Juan",
        "piloto": "Scoltore, Juan",
        "marca": "CHEVROLET",
        "vueltas": "0",
        "tiempo": "",
        "diferencia": "20 VTAS",
        "nacionalidad": "Scoltore, Juan"
      },
      {
        "pos": "33°",
        "nro": "123",
        "nombre": "Gonnet,",
        "apellido": "Gerónimo",
        "piloto": "Gonnet, Gerónimo",
        "marca": "Torino",
        "vueltas": "0",
        "tiempo": "",
        "diferencia": "20 VTAS",
        "nacionalidad": "Gonnet, Gerónimo"
      },
      {
        "pos": "34°",
        "nro": "131",
        "nombre": "Rasuk,",
        "apellido": "José",
        "piloto": "Rasuk, José",
        "marca": "Dodge",
        "vueltas": "0",
        "tiempo": "",
        "diferencia": "20 VTAS",
        "nacionalidad": "Rasuk, José"
      }
    ]
  },
  {
    "url": "https://actc.org.ar/v3/carrera-on-line-resultados.ajax.php?intIDCarrera=1517&intIDTanda=15",
    "resultado": []
  },
  {
    "url": "https://actc.org.ar/v3/carrera-on-line-resultados.ajax.php?intIDCarrera=1518&intIDTanda=15",
    "resultado": []
  },
  {
    "url": "https://actc.org.ar/v3/carrera-on-line-resultados.ajax.php?intIDCarrera=1519&intIDTanda=15",
    "resultado": []
  },
  {
    "url": "https://actc.org.ar/v3/carrera-on-line-resultados.ajax.php?intIDCarrera=1520&intIDTanda=15",
    "resultado": []
  },
  {
    "url": "https://actc.org.ar/v3/carrera-on-line-resultados.ajax.php?intIDCarrera=1521&intIDTanda=15",
    "resultado": []
  },
  {
    "url": "https://actc.org.ar/v3/carrera-on-line-resultados.ajax.php?intIDCarrera=1522&intIDTanda=15",
    "resultado": []
  },
  {
    "url": "https://actc.org.ar/v3/carrera-on-line-resultados.ajax.php?intIDCarrera=1523&intIDTanda=15",
    "resultado": []
  },
  {
    "url": "https://actc.org.ar/v3/carrera-on-line-resultados.ajax.php?intIDCarrera=1524&intIDTanda=15",
    "resultado": []
  }
]